microst/__init__.py
microst/__main__.py
microst/microst.py
microst-0.1.1.dist-info/LICENSE
microst-0.1.1.dist-info/METADATA
microst-0.1.1.dist-info/WHEEL
microst-0.1.1.dist-info/entry_points.txt
microst-0.1.1.dist-info/top_level.txt
microst-0.1.1.dist-info/zip-safe
microst-0.1.1.dist-info/RECORD
