Metadata-Version: 2.1
Name: microst
Version: 0.1.1
Summary: micro serial terminal
Home-page: https://github.com/Garfield1002/microst
Author: Jack Royer
Author-email: jack.royer.23@gmail.com
License: MIT
Keywords: serial,terminal
Platform: UNKNOWN
Classifier: Programming Language :: Python :: 3
Classifier: License :: OSI Approved :: MIT License
Classifier: Operating System :: OS Independent
Requires-Dist: pyserial
